codex_mcp_agent/__main__.py
codex_mcp_agent/prompts.py
codex_mcp_agent/server.py
codex_mcp_agent/utils.py
codex_mcp_agent/tools/__init__.py
codex_mcp_agent/tools/codex_execute.py
codex_mcp_agent/tools/codex_research.py
codex_mcp_agent/tools/codex_review.py
codex_mcp_agent-0.1.0.dist-info/METADATA
codex_mcp_agent-0.1.0.dist-info/WHEEL
codex_mcp_agent-0.1.0.dist-info/entry_points.txt
codex_mcp_agent-0.1.0.dist-info/RECORD
