Metadata-Version: 2.4
Name: codex-mcp-agent
Version: 0.1.0
Summary: MCP server that provides agent capability backing by codex CLI
Project-URL: Homepage, https://github.com/1WorldCapture/codex-as-mcp
Project-URL: Repository, https://github.com/1WorldCapture/codex-as-mcp
Project-URL: Issues, https://github.com/1WorldCapture/codex-as-mcp/issues
Author-email: Lyon Liang <lyon.liang12@gmail.com>
Keywords: agent,codex,mcp
Classifier: Development Status :: 3 - Alpha
Classifier: Intended Audience :: Developers
Classifier: License :: OSI Approved :: MIT License
Classifier: Programming Language :: Python :: 3
Classifier: Programming Language :: Python :: 3.11
Classifier: Programming Language :: Python :: 3.12
Requires-Python: >=3.11
Requires-Dist: mcp[cli]>=1.12.4
Requires-Dist: uvicorn>=0.30.0
